coronagraph/Noise.py
coronagraph/__init__.py
coronagraph/convolve_spec.py
coronagraph/count_rates.py
coronagraph/count_rates_wrapper.py
coronagraph/degrade_spec.py
coronagraph/imager.py
coronagraph/noise_routines.py
coronagraph/observe.py
coronagraph/plot_setup.py
coronagraph/teleplanstar.py
coronagraph/transits.py
coronagraph/ground/earth_thermal.txt
coronagraph/ground/earth_thermal_atacama_30deg.txt
coronagraph/ground/earth_transmission.txt
coronagraph/ground/earth_transmission_atacama_30deg.txt
coronagraph/inputs/input_default_planet.py
coronagraph/inputs/input_default_star.py
coronagraph/inputs/input_default_telescope.py
coronagraph/inputs/input_user_planet.py
coronagraph/inputs/input_user_star.py
coronagraph/inputs/input_user_telescope.py
coronagraph/planets/ArcheanEarth_geo_albedo.txt
coronagraph/planets/EarlyMars_geo_albedo.txt
coronagraph/planets/EarlyVenus_geo_albedo.txt
coronagraph/planets/F2V_5.e-1fCO2_1.e6H2Volc_1.e10BIF.out_toa.rad
coronagraph/planets/Hazy_ArcheanEarth_geo_albedo.txt
coronagraph/planets/Jupiter_geo_albedo.txt
coronagraph/planets/Mars_geo_albedo.txt
coronagraph/planets/Neptune_geo_albedo.txt
coronagraph/planets/Saturn_geo_albedo.txt
coronagraph/planets/Uranus_geo_albedo.txt
coronagraph/planets/Venus_geo_albedo.txt
coronagraph/planets/earth_avg_hitran2012_300_100000cm.trnst
coronagraph/planets/earth_avg_hitran2012_300_100000cm_toa.rad
coronagraph/planets/earth_quadrature_radiance_refl.dat
coronagraph/planets/fstarcloudy.sav
coronagraph/planets/jupiter.txt
coronagraph/planets/saturn.txt
coronagraph/planets/subneptune.txt
coronagraph/planets/uranus.txt
coronagraph/planets/wavelengths.txt
coronagraph/tests/__init__.py
coronagraph/tests/test_coronagraph.py
coronagraph-1.1.data/data/ArcheanEarth_geo_albedo.txt
coronagraph-1.1.data/data/EarlyMars_geo_albedo.txt
coronagraph-1.1.data/data/EarlyVenus_geo_albedo.txt
coronagraph-1.1.data/data/Hazy_ArcheanEarth_geo_albedo.txt
coronagraph-1.1.dist-info/DESCRIPTION.rst
coronagraph-1.1.dist-info/METADATA
coronagraph-1.1.dist-info/RECORD
coronagraph-1.1.dist-info/WHEEL
coronagraph-1.1.dist-info/metadata.json
coronagraph-1.1.dist-info/top_level.txt
