Metadata-Version: 2.0
Name: coronagraph
Version: 1.1
Summary: Coronagraph noise model for directly imaging exoplanets.
Home-page: http://github.com/jlustigy/coronagraph
Author: Jacob Lustig-Yaeger
Author-email: jlustigy@uw.edu
License: MIT
Platform: UNKNOWN
Classifier: Development Status :: 3 - Alpha
Classifier: Programming Language :: Python
Classifier: Programming Language :: Python :: 3
Classifier: License :: OSI Approved :: MIT License
Classifier: Topic :: Scientific/Engineering :: Astronomy
Requires-Dist: numpy
Requires-Dist: scipy
Requires-Dist: matplotlib
Requires-Dist: numba
Requires-Dist: astropy
